vaslui/__init__.py
vaslui-0.1.0.dist-info/WHEEL
vaslui-0.1.0.dist-info/entry_points.txt
vaslui-0.1.0.dist-info/METADATA
vaslui-0.1.0.dist-info/RECORD
