Metadata-Version: 2.3
Name: vaslui
Version: 0.1.0
Summary: vaslui
Requires-Python: >=3.12
